nithesh_house_prices/__init__.py
nithesh_house_prices/inference.py
nithesh_house_prices/preprocess.py
nithesh_house_prices/train.py
nithesh_house_prices-0.1.0.dist-info/METADATA
nithesh_house_prices-0.1.0.dist-info/WHEEL
nithesh_house_prices-0.1.0.dist-info/licenses/LICENSE
nithesh_house_prices-0.1.0.dist-info/RECORD
